lab01_cyb600_nj/__init__.py
lab01_cyb600_nj/main.py
lab01_cyb600_nj-1.1.data/scripts/say-hello-cyb600
lab01_cyb600_nj-1.1.dist-info/METADATA
lab01_cyb600_nj-1.1.dist-info/WHEEL
lab01_cyb600_nj-1.1.dist-info/top_level.txt
lab01_cyb600_nj-1.1.dist-info/RECORD
