Metadata-Version: 2.1
Name: lab01_cyb600_nj
Version: 1.1
Author: Nsundidi Jorge
Author-email: jorgen@canisius.edu
License: Apache License Version 2.0
